<annotation>
	<folder>AlertSampleE-night</folder>
	<filename>AlertSampleE-20.jpg</filename>
	<path>C:/Users/Administrator/Desktop/AlertSampleE-night/AlertSampleE-20.jpg</path>
	<source>
		<database>Unknown</database>
	</source>
	<size>
		<width>1280</width>
		<height>720</height>
		<depth>3</depth>
	</size>
	<segmented>0</segmented>
	<object>
		<name>person</name>
		<pose>Unspecified</pose>
		<truncated>0</truncated>
		<difficult>0</difficult>
		<bndbox>
			<xmin>681</xmin>
			<ymin>33</ymin>
			<xmax>934</xmax>
			<ymax>433</ymax>
		</bndbox>
	</object>
	<object>
		<name>youtong</name>
		<pose>Unspecified</pose>
		<truncated>0</truncated>
		<difficult>0</difficult>
		<bndbox>
			<xmin>745</xmin>
			<ymin>296</ymin>
			<xmax>782</xmax>
			<ymax>380</ymax>
		</bndbox>
	</object>
	<object>
		<name>person</name>
		<pose>Unspecified</pose>
		<truncated>1</truncated>
		<difficult>0</difficult>
		<bndbox>
			<xmin>636</xmin>
			<ymin>1</ymin>
			<xmax>704</xmax>
			<ymax>183</ymax>
		</bndbox>
	</object>
	<object>
		<name>youtong</name>
		<pose>Unspecified</pose>
		<truncated>0</truncated>
		<difficult>0</difficult>
		<bndbox>
			<xmin>606</xmin>
			<ymin>24</ymin>
			<xmax>666</xmax>
			<ymax>95</ymax>
		</bndbox>
	</object>
</annotation>
