<annotation>
	<folder>50张</folder>
	<filename>2022-06-08 17-24-19.jpg</filename>
	<path>H:/50张/2022-06-08 17-24-19.jpg</path>
	<source>
		<database>Unknown</database>
	</source>
	<size>
		<width>1280</width>
		<height>720</height>
		<depth>3</depth>
	</size>
	<segmented>0</segmented>
	<object>
		<name>paomozhipin</name>
		<pose>Unspecified</pose>
		<truncated>1</truncated>
		<difficult>0</difficult>
		<bndbox>
			<xmin>7</xmin>
			<ymin>284</ymin>
			<xmax>243</xmax>
			<ymax>720</ymax>
		</bndbox>
	</object>
	<object>
		<name>paomozhipin</name>
		<pose>Unspecified</pose>
		<truncated>1</truncated>
		<difficult>0</difficult>
		<bndbox>
			<xmin>132</xmin>
			<ymin>508</ymin>
			<xmax>541</xmax>
			<ymax>720</ymax>
		</bndbox>
	</object>
	<object>
		<name>person</name>
		<pose>Unspecified</pose>
		<truncated>1</truncated>
		<difficult>0</difficult>
		<bndbox>
			<xmin>491</xmin>
			<ymin>449</ymin>
			<xmax>704</xmax>
			<ymax>720</ymax>
		</bndbox>
	</object>
	<object>
		<name>worker</name>
		<pose>Unspecified</pose>
		<truncated>0</truncated>
		<difficult>0</difficult>
		<bndbox>
			<xmin>458</xmin>
			<ymin>180</ymin>
			<xmax>670</xmax>
			<ymax>601</ymax>
		</bndbox>
	</object>
	<object>
		<name>person</name>
		<pose>Unspecified</pose>
		<truncated>0</truncated>
		<difficult>0</difficult>
		<bndbox>
			<xmin>835</xmin>
			<ymin>71</ymin>
			<xmax>929</xmax>
			<ymax>358</ymax>
		</bndbox>
	</object>
	<object>
		<name>mianzhipin</name>
		<pose>Unspecified</pose>
		<truncated>0</truncated>
		<difficult>0</difficult>
		<bndbox>
			<xmin>914</xmin>
			<ymin>199</ymin>
			<xmax>948</xmax>
			<ymax>312</ymax>
		</bndbox>
	</object>
	<object>
		<name>person</name>
		<pose>Unspecified</pose>
		<truncated>0</truncated>
		<difficult>0</difficult>
		<bndbox>
			<xmin>521</xmin>
			<ymin>105</ymin>
			<xmax>610</xmax>
			<ymax>269</ymax>
		</bndbox>
	</object>
	<object>
		<name>paomozhipin</name>
		<pose>Unspecified</pose>
		<truncated>0</truncated>
		<difficult>0</difficult>
		<bndbox>
			<xmin>662</xmin>
			<ymin>308</ymin>
			<xmax>720</xmax>
			<ymax>352</ymax>
		</bndbox>
	</object>
</annotation>
