<annotation>
	<folder>其它</folder>
	<filename>2022-06-19 11-02-06.jpg</filename>
	<path>C:/Users/Administrator/Desktop/打标/4/其它/2022-06-19 11-02-06.jpg</path>
	<source>
		<database>Unknown</database>
	</source>
	<size>
		<width>1280</width>
		<height>720</height>
		<depth>3</depth>
	</size>
	<segmented>0</segmented>
	<object>
		<name>person</name>
		<pose>Unspecified</pose>
		<truncated>0</truncated>
		<difficult>0</difficult>
		<bndbox>
			<xmin>562</xmin>
			<ymin>363</ymin>
			<xmax>672</xmax>
			<ymax>675</ymax>
		</bndbox>
	</object>
	<object>
		<name>person</name>
		<pose>Unspecified</pose>
		<truncated>1</truncated>
		<difficult>0</difficult>
		<bndbox>
			<xmin>34</xmin>
			<ymin>290</ymin>
			<xmax>404</xmax>
			<ymax>720</ymax>
		</bndbox>
	</object>
	<object>
		<name>worker</name>
		<pose>Unspecified</pose>
		<truncated>0</truncated>
		<difficult>0</difficult>
		<bndbox>
			<xmin>305</xmin>
			<ymin>176</ymin>
			<xmax>478</xmax>
			<ymax>705</ymax>
		</bndbox>
	</object>
	<object>
		<name>person</name>
		<pose>Unspecified</pose>
		<truncated>0</truncated>
		<difficult>0</difficult>
		<bndbox>
			<xmin>1020</xmin>
			<ymin>68</ymin>
			<xmax>1115</xmax>
			<ymax>413</ymax>
		</bndbox>
	</object>
	<object>
		<name>zhizhipin</name>
		<pose>Unspecified</pose>
		<truncated>0</truncated>
		<difficult>0</difficult>
		<bndbox>
			<xmin>739</xmin>
			<ymin>465</ymin>
			<xmax>843</xmax>
			<ymax>552</ymax>
		</bndbox>
	</object>
	<object>
		<name>garbage-bag</name>
		<pose>Unspecified</pose>
		<truncated>0</truncated>
		<difficult>0</difficult>
		<bndbox>
			<xmin>783</xmin>
			<ymin>442</ymin>
			<xmax>883</xmax>
			<ymax>487</ymax>
		</bndbox>
	</object>
	<object>
		<name>garbage-bag</name>
		<pose>Unspecified</pose>
		<truncated>0</truncated>
		<difficult>0</difficult>
		<bndbox>
			<xmin>764</xmin>
			<ymin>547</ymin>
			<xmax>860</xmax>
			<ymax>585</ymax>
		</bndbox>
	</object>
	<object>
		<name>suliaozhipin</name>
		<pose>Unspecified</pose>
		<truncated>0</truncated>
		<difficult>0</difficult>
		<bndbox>
			<xmin>903</xmin>
			<ymin>196</ymin>
			<xmax>998</xmax>
			<ymax>394</ymax>
		</bndbox>
	</object>
</annotation>
