<annotation>
	<folder>AlertSampleC</folder>
	<filename>AlertSampleC-356.jpg</filename>
	<path>C:/沈/AlertSampleC/AlertSampleC-356.jpg</path>
	<source>
		<database>Unknown</database>
	</source>
	<size>
		<width>1920</width>
		<height>1080</height>
		<depth>3</depth>
	</size>
	<segmented>0</segmented>
	<object>
		<name>suliaozhipin</name>
		<pose>Unspecified</pose>
		<truncated>0</truncated>
		<difficult>0</difficult>
		<bndbox>
			<xmin>852</xmin>
			<ymin>628</ymin>
			<xmax>931</xmax>
			<ymax>676</ymax>
		</bndbox>
	</object>
	<object>
		<name>paomozhipin</name>
		<pose>Unspecified</pose>
		<truncated>0</truncated>
		<difficult>0</difficult>
		<bndbox>
			<xmin>961</xmin>
			<ymin>630</ymin>
			<xmax>1045</xmax>
			<ymax>710</ymax>
		</bndbox>
	</object>
	<object>
		<name>zhizhipin</name>
		<pose>Unspecified</pose>
		<truncated>0</truncated>
		<difficult>0</difficult>
		<bndbox>
			<xmin>968</xmin>
			<ymin>720</ymin>
			<xmax>1028</xmax>
			<ymax>762</ymax>
		</bndbox>
	</object>
	<object>
		<name>person</name>
		<pose>Unspecified</pose>
		<truncated>0</truncated>
		<difficult>0</difficult>
		<bndbox>
			<xmin>1225</xmin>
			<ymin>279</ymin>
			<xmax>1400</xmax>
			<ymax>786</ymax>
		</bndbox>
	</object>
</annotation>
